plot_cli/__init__.py
plot_cli/config.py
plot_cli/core.py
plot_cli/options.py
plot_cli-0.2.0.dist-info/entry_points.txt
plot_cli-0.2.0.dist-info/LICENSE
plot_cli-0.2.0.dist-info/WHEEL
plot_cli-0.2.0.dist-info/METADATA
plot_cli-0.2.0.dist-info/RECORD
