Metadata-Version: 2.1
Name: plot-cli
Version: 0.2.0
Summary: Command Line Interface for Data Visualization
Home-page: https://github.com/xkumiyu/plot-cli
License: MIT
Author: xkumiyu
Author-email: xkumiyu@gmail.com
Requires-Python: >=3.6.1,<4
Classifier: Environment :: Console
Classifier: License :: OSI Approved :: MIT License
Classifier: Programming Language :: Python :: 3
Classifier: Programming Language :: Python :: 3.6
Classifier: Programming Language :: Python :: 3.7
Classifier: Programming Language :: Python :: 3.8
Classifier: Topic :: Utilities
Requires-Dist: click (>=7.1.1,<8.0.0)
Requires-Dist: matplotlib (>=3.2.0,<4.0.0)
Requires-Dist: pandas (>=1.0.1,<2.0.0)
Project-URL: Repository, https://github.com/xkumiyu/plot-cli
